mdfa/__init__.py
mdfa/mdfa.py
mdfa-0.1.0.dist-info/LICENSE
mdfa-0.1.0.dist-info/METADATA
mdfa-0.1.0.dist-info/WHEEL
mdfa-0.1.0.dist-info/top_level.txt
mdfa-0.1.0.dist-info/RECORD
