Metadata-Version: 2.1
Name: mdfa
Version: 0.1.0
Summary: MDFA: A Multi-Dimensional Feature Attention model
Home-page: https://github.com/yourusername/your_project
Author: backy
Author-email: backywen@163.com
Classifier: Programming Language :: Python :: 3
Classifier: License :: OSI Approved :: MIT License
Classifier: Operating System :: OS Independent
Requires-Python: >=3.6
License-File: LICENSE
Requires-Dist: torch>=1.7.0
